example_pkg4/__init__.py
example_pkg4/compo1.py
example_pkg4/compo2.py
test/__init__.py
example_pkg4-0.0.1.dist-info/LICENSE
example_pkg4-0.0.1.dist-info/METADATA
example_pkg4-0.0.1.dist-info/WHEEL
example_pkg4-0.0.1.dist-info/top_level.txt
example_pkg4-0.0.1.dist-info/RECORD
